kitconcept/__init__.py
kitconcept/voltolighttheme/__init__.py
kitconcept/voltolighttheme/configure.zcml
kitconcept/voltolighttheme/dependencies.zcml
kitconcept/voltolighttheme/interfaces.py
kitconcept/voltolighttheme/profiles.zcml
kitconcept/voltolighttheme/testing.py
kitconcept/voltolighttheme/behaviors/__init__.py
kitconcept/voltolighttheme/behaviors/configure.zcml
kitconcept/voltolighttheme/behaviors/customizations.py
kitconcept/voltolighttheme/behaviors/footer.py
kitconcept/voltolighttheme/behaviors/sticky_menu.py
kitconcept/voltolighttheme/locales/__init__.py
kitconcept/voltolighttheme/locales/__main__.py
kitconcept/voltolighttheme/locales/kitconcept.voltolighttheme.pot
kitconcept/voltolighttheme/locales/de/LC_MESSAGES/kitconcept.voltolighttheme.mo
kitconcept/voltolighttheme/locales/de/LC_MESSAGES/kitconcept.voltolighttheme.po
kitconcept/voltolighttheme/locales/en/LC_MESSAGES/kitconcept.voltolighttheme.mo
kitconcept/voltolighttheme/locales/en/LC_MESSAGES/kitconcept.voltolighttheme.po
kitconcept/voltolighttheme/locales/es/LC_MESSAGES/kitconcept.voltolighttheme.mo
kitconcept/voltolighttheme/locales/es/LC_MESSAGES/kitconcept.voltolighttheme.po
kitconcept/voltolighttheme/locales/eu/LC_MESSAGES/kitconcept.voltolighttheme.mo
kitconcept/voltolighttheme/locales/eu/LC_MESSAGES/kitconcept.voltolighttheme.po
kitconcept/voltolighttheme/locales/pt_BR/LC_MESSAGES/kitconcept.voltolighttheme.mo
kitconcept/voltolighttheme/locales/pt_BR/LC_MESSAGES/kitconcept.voltolighttheme.po
kitconcept/voltolighttheme/profiles/acceptance/metadata.xml
kitconcept/voltolighttheme/profiles/acceptance/theme.xml
kitconcept/voltolighttheme/profiles/acceptance/types.xml
kitconcept/voltolighttheme/profiles/acceptance/types/.gitkeep
kitconcept/voltolighttheme/profiles/acceptance/types/Document.xml
kitconcept/voltolighttheme/profiles/acceptance/types/News_Item.xml
kitconcept/voltolighttheme/profiles/acceptance/types/Plone_Site.xml
kitconcept/voltolighttheme/profiles/default/browserlayer.xml
kitconcept_voltolighttheme-7.6.7.dist-info/METADATA
kitconcept_voltolighttheme-7.6.7.dist-info/WHEEL
kitconcept_voltolighttheme-7.6.7.dist-info/entry_points.txt
kitconcept_voltolighttheme-7.6.7.dist-info/licenses/LICENSE.GPL
kitconcept_voltolighttheme-7.6.7.dist-info/licenses/LICENSE.md
kitconcept_voltolighttheme-7.6.7.dist-info/RECORD
