Metadata-Version: 2.4
Name: kitconcept.voltolighttheme
Version: 7.6.7
Summary: Plone package providing features for @kitconcept/volto-light-theme
Project-URL: Homepage, https://github.com/kitconcept/volto-light-theme
Project-URL: Documentation, https://volto-light-theme.readthedocs.io/
Project-URL: PyPI, https://pypi.org/project/kitconcept.voltolighttheme
Project-URL: Source, https://github.com/kitconcept/volto-light-theme
Project-URL: Tracker, https://github.com/kitconcept/volto-light-theme/issues
Author-email: kitconcept GmbH <contact@kitconcept.com>
License-Expression: GPL-2.0-only
License-File: LICENSE.GPL
License-File: LICENSE.md
Keywords: CMS,Plone,Volto
Classifier: Development Status :: 3 - Alpha
Classifier: Environment :: Web Environment
Classifier: Framework :: Plone
Classifier: Framework :: Plone :: 6.0
Classifier: Framework :: Plone :: 6.1
Classifier: Framework :: Plone :: Addon
Classifier: License :: OSI Approved :: GNU General Public License v2 (GPLv2)
Classifier: Operating System :: OS Independent
Classifier: Programming Language :: Python
Classifier: Programming Language :: Python :: 3.12
Classifier: Programming Language :: Python :: 3.13
Requires-Python: >=3.12
Requires-Dist: plone-api
Requires-Dist: plone-restapi>=9.13.2
Requires-Dist: plone-volto
Requires-Dist: plonegovbr-socialmedia>=2.0.0a10
Requires-Dist: products-cmfplone>=6.0
Provides-Extra: demo
Requires-Dist: plone-exportimport; extra == 'demo'
Provides-Extra: test
Requires-Dist: plone-app-testing; extra == 'test'
Requires-Dist: plone-exportimport; extra == 'test'
Requires-Dist: plone-restapi[test]; extra == 'test'
Requires-Dist: pytest; extra == 'test'
Requires-Dist: pytest-cov; extra == 'test'
Requires-Dist: pytest-plone>=0.5.0; extra == 'test'
